pysesame/__init__.py
pysesame/candyhouse.py
pysesame/sesame.py
pysesame-0.2.0.dist-info/DESCRIPTION.rst
pysesame-0.2.0.dist-info/METADATA
pysesame-0.2.0.dist-info/RECORD
pysesame-0.2.0.dist-info/WHEEL
pysesame-0.2.0.dist-info/metadata.json
pysesame-0.2.0.dist-info/top_level.txt
pysesame-0.2.0.dist-info/zip-safe
