Metadata-Version: 2.0
Name: pysesame
Version: 0.2.0
Summary: Python API for Sesame smart locks
Home-page: https://github.com/trisk/pysesame
Author: Albert Lee
Author-email: trisk@forkgnu.org
License: MIT
Platform: any
Classifier: Development Status :: 4 - Beta
Classifier: Intended Audience :: Developers
Classifier: Topic :: Software Development :: Libraries :: Python Modules
Classifier: Topic :: Home Automation
Classifier: License :: OSI Approved :: MIT License
Classifier: Operating System :: OS Independent
Classifier: Programming Language :: Python
Classifier: Programming Language :: Python :: 2
Classifier: Programming Language :: Python :: 3
Requires-Dist: requests (>=0.10.7)
